{
    "resourceType": "DiagnosticReport",
    "id": "4fb48baf-47b4-4da6-aa21-ad278fc60747",
    "meta": {
        "profile": [
            "http://hl7.org/fhir/us/core/StructureDefinition/us-core-diagnosticreport-lab"
        ]
    },
    "status": "final",
    "category": [
        {
            "coding": [
                {
                    "system": "http://terminology.hl7.org/CodeSystem/v2-0074",
                    "code": "LAB",
                    "display": "Laboratory"
                }
            ]
        }
    ],
    "code": {
        "coding": [
            {
                "system": "http://loinc.org",
                "code": "51990-0",
                "display": "Basic Metabolic Panel"
            }
        ],
        "text": "Basic Metabolic Panel"
    },
    "subject": {
        "reference": "Patient/3ab28624-a549-4cb9-a32e-99e3c2c41129"
    },
    "encounter": {
        "reference": "Encounter/e2e600a8-64d8-4f13-aa7b-906068dbf4c0"
    },
    "effectiveDateTime": "2013-12-24T15:16:44-08:00",
    "issued": "2013-12-24T15:16:44.618-08:00",
    "result": [
        {
            "reference": "Observation/ed02650a-13b9-4814-bf27-c23bdb7183d8",
            "display": "Glucose"
        },
        {
            "reference": "Observation/ba018dce-3bfd-4a24-bb62-3505a76f6424",
            "display": "Urea Nitrogen"
        },
        {
            "reference": "Observation/b42ebcae-8ec6-4d90-a767-44bae96be4b6",
            "display": "Creatinine"
        },
        {
            "reference": "Observation/a351ac89-17e3-4f7e-af4a-54fd07036288",
            "display": "Calcium"
        },
        {
            "reference": "Observation/89c9e6ab-23cb-46ea-b41e-3976e666ca9c",
            "display": "Sodium"
        },
        {
            "reference": "Observation/006bc617-1e7c-4fb2-89f0-c27d10f24e78",
            "display": "Potassium"
        },
        {
            "reference": "Observation/1fdad957-4286-4bef-b227-66b450b75f18",
            "display": "Chloride"
        },
        {
            "reference": "Observation/c0419fef-b88d-45ec-9604-b73ee25b374b",
            "display": "Carbon Dioxide"
        }
    ]
}