{
  "resourceType": "Observation",
  "id": "9e68f54f-d3cb-458e-89cb-80a8421c50c1",
  "meta": {
    "profile": [
      "http://hl7.org/fhir/StructureDefinition/vitalsigns"
    ]
  },
  "text": {
    "status": "generated",
    "div": "<div xmlns=\"http://www.w3.org/1999/xhtml\"><p><b>Generated Narrative with Details</b></p><p><b>id</b>: 9e68f54f-d3cb-458e-89cb-80a8421c50c1</p><p><b>meta</b>: </p><p><b>status</b>: final</p><p><b>category</b>: vital-signs <span style=\"background: LightGoldenRodYellow\">(Details : {http://terminology.hl7.org/CodeSystem/observation-category code 'vital-signs' = 'Vital Signs', given as 'vital-signs'})</span></p><p><b>code</b>: Pain severity - 0-10 verbal numeric rating [Score] - Reported <span style=\"background: LightGoldenRodYellow\">(Details : {LOINC code '72514-3' = 'Pain severity - 0-10 verbal numeric rating [Score] - Reported', given as 'Pain severity - 0-10 verbal numeric rating [Score] - Reported'})</span></p><p><b>subject</b>: <a href=\"Patient-8b42051b-e45b-4032-926a-747affe4e09d.html\">Generated Summary: id: 8b42051b-e45b-4032-926a-747affe4e09d; ffd13be6-c334-4ede-bea5-2cd7d569b71f, Medical Record Number = ffd13be6-c334-4ede-bea5-2cd7d569b71f, Social Security Number = 999-95-3799, Driver's License = S99927323, Passport Number = X48434749X; Phillip440 Ullrich385 (OFFICIAL); ph: 555-841-8167(HOME); gender: male; birthDate: Mar 7, 1947; <span title=\"Codes: {http://terminology.hl7.org/CodeSystem/v3-MaritalStatus M}\">M</span>; </a></p><p><b>encounter</b>: <a href=\"Encounter-6a4741ed-47a2-4afb-9f21-af445dd543f1.html\">Generated Summary: id: 6a4741ed-47a2-4afb-9f21-af445dd543f1; status: finished; <span title=\"{http://terminology.hl7.org/CodeSystem/v3-ActCode AMB}\">ambulatory</span>; <span title=\"Codes: {http://snomed.info/sct 185347001}\">Encounter for problem</span>; period: Feb 18, 2016, 12:46:03 PM --&gt; Feb 18, 2016, 1:01:03 PM; <span title=\"Codes: {http://snomed.info/sct 90560007}\">Gout</span></a></p><p><b>effective</b>: Feb 18, 2016, 12:46:03 PM</p><p><b>issued</b>: Feb 18, 2016, 12:46:03 PM</p><p><b>value</b>: 6.390509915456786 {score}<span style=\"background: LightGoldenRodYellow\"> (Details: UCUM code {score} = '{score}')</span></p></div>"
  },
  "status": "final",
  "category": [
    {
      "coding": [
        {
          "system": "http://terminology.hl7.org/CodeSystem/observation-category",
          "code": "vital-signs",
          "display": "vital-signs"
        }
      ]
    }
  ],
  "code": {
    "coding": [
      {
        "system": "http://loinc.org",
        "code": "72514-3",
        "display": "Pain severity - 0-10 verbal numeric rating [Score] - Reported"
      }
    ],
    "text": "Pain severity - 0-10 verbal numeric rating [Score] - Reported"
  },
  "subject": {
    "reference": "Patient/8b42051b-e45b-4032-926a-747affe4e09d"
  },
  "encounter": {
    "reference": "Encounter/6a4741ed-47a2-4afb-9f21-af445dd543f1"
  },
  "effectiveDateTime": "2016-02-18T12:46:03-08:00",
  "issued": "2016-02-18T12:46:03.598-08:00",
  "valueQuantity": {
    "value": 6.390509915456786,
    "unit": "{score}",
    "system": "http://unitsofmeasure.org",
    "code": "{score}"
  }
}